pynif/__init__.py
pynif/collection.py
pynif/context.py
pynif/phrase.py
pynif/prefixes.py
pynif/tests/__init__.py
pynif/tests/test_collection.py
pynif/tests/test_context.py
pynif/tests/test_phrase.py
pynif/tests/util.py
pynif-0.3.1.dist-info/LICENSE
pynif-0.3.1.dist-info/METADATA
pynif-0.3.1.dist-info/WHEEL
pynif-0.3.1.dist-info/top_level.txt
pynif-0.3.1.dist-info/RECORD
