Metadata-Version: 2.1
Name: pynif
Version: 0.3.1
Summary: A small Python library for the NLP Interchange Format (NIF) 
Home-page: https://github.com/wetneb/pynif
Author: Antonin Delpeuch
Author-email: antonin@delpeuch.eu
License: Apache v2.0
Keywords: NIF-Lib NIF NLP formats NER RDF
Classifier: Development Status :: 3 - Alpha
Classifier: Intended Audience :: Developers
Classifier: Topic :: Scientific/Engineering :: Information Analysis
Classifier: License :: OSI Approved :: Apache Software License
Classifier: Programming Language :: Python :: 2
Classifier: Programming Language :: Python :: 2.7
Classifier: Programming Language :: Python :: 3
Classifier: Programming Language :: Python :: 3.3
Classifier: Programming Language :: Python :: 3.4
Classifier: Programming Language :: Python :: 3.5
Classifier: Programming Language :: Python :: 3.6
Classifier: Programming Language :: Python :: 3.7
License-File: LICENSE
Requires-Dist: rdflib
Provides-Extra: dev
Requires-Dist: check-manifest ; extra == 'dev'
Provides-Extra: test
Requires-Dist: pytest-cov ; extra == 'test'
Requires-Dist: pytest ; extra == 'test'
